ViyaCasual/Casual.py
ViyaCasual/Database.py
ViyaCasual/__init__.py
ViyaCasual/temp.building.py
ViyaCasual/temp.cleanup.py
ViyaCasual/CAS/CAS.py
ViyaCasual/CAS/CASDecisionBase.py
ViyaCasual/CAS/CASLibraryBase.py
ViyaCasual/CAS/CASTableBase.py
ViyaCasual/CAS/__init__.py
ViyaCasual/Viya/ViyaConnection.py
ViyaCasual/Viya/ViyaConnectionExceptions.py
ViyaCasual/Viya/__init__.py
ViyalCasual/Casual.py
ViyalCasual/Database.py
ViyalCasual/__init__.py
ViyalCasual/CAS/CAS.py
ViyalCasual/CAS/CASDecisionBase.py
ViyalCasual/CAS/CASTableBase.py
ViyalCasual/CAS/__init__.py
ViyalCasual/Viya/ViyaConnection.py
ViyalCasual/Viya/ViyaConnectionExceptions.py
ViyalCasual/Viya/__init__.py
ViyaCASual_BNE-0.0.221.dist-info/LICENSE
ViyaCASual_BNE-0.0.221.dist-info/METADATA
ViyaCASual_BNE-0.0.221.dist-info/WHEEL
ViyaCASual_BNE-0.0.221.dist-info/top_level.txt
ViyaCASual_BNE-0.0.221.dist-info/RECORD
