Metadata-Version: 2.1
Name: ViyaCASual-BNE
Version: 0.0.221
Summary: UNKNOWN
Home-page: https://github.com/willhaley-bne/ViyaCasual
Author: Will Haley
Author-email: willhaley@boddienoell.com
License: UNKNOWN
Platform: UNKNOWN
Classifier: Programming Language :: Python :: 3
Classifier: License :: OSI Approved :: MIT License
Classifier: Operating System :: OS Independent
Requires-Python: >=3.6
